README.rst
process_ring.py
setup.py
__multiprocessing/__init__.py
__multiprocessing/connection.py
__multiprocessing/forking.py
__multiprocessing/heap.py
__multiprocessing/managers.py
__multiprocessing/pool.py
__multiprocessing/process.py
__multiprocessing/queues.py
__multiprocessing/reduction.py
__multiprocessing/sharedctypes.py
__multiprocessing/synchronize.py
__multiprocessing/util.py
__multiprocessing/dummy/__init__.py
__multiprocessing/dummy/connection.py
paragram/__init__.py
paragram/graph.py
paragram/managers.py
paragram/pattern.py
paragram/receiver.py
paragram.egg-info/PKG-INFO
paragram.egg-info/SOURCES.txt
paragram.egg-info/dependency_links.txt
paragram.egg-info/requires.txt
paragram.egg-info/top_level.txt
paragram/process/__init__.py
paragram/process/base_process.py
paragram/process/main.py
paragram/process/os_process.py
paragram/process/thread_process.py