Metadata-Version: 1.0
Name: paragram
Version: 0.1.2
Summary: erlang-style concurrency library for python
Home-page: http://gfxmonk.net/dist/0install/paragram.xml
Author: UNKNOWN
Author-email: UNKNOWN
License: UNKNOWN
Platform: UNKNOWN
